lib_test/__init__.py
lib_test/dummy.py
dummy_ci_cd-0.1.0.dist-info/METADATA
dummy_ci_cd-0.1.0.dist-info/WHEEL
dummy_ci_cd-0.1.0.dist-info/entry_points.txt
dummy_ci_cd-0.1.0.dist-info/RECORD
