Metadata-Version: 2.1
Name: dummy-ci-cd
Version: 0.1.0
Summary: A CI/CD demo project
Author: the-reacher-data
Author-email: massivedatascope@gmail.com
Requires-Python: >=3.11,<4.0
Classifier: Programming Language :: Python :: 3
Classifier: Programming Language :: Python :: 3.11
Classifier: Programming Language :: Python :: 3.12
Classifier: Programming Language :: Python :: 3.13
